lsat/__init__.py
lsat-0.0.1.dist-info/LICENCE
lsat-0.0.1.dist-info/METADATA
lsat-0.0.1.dist-info/WHEEL
lsat-0.0.1.dist-info/top_level.txt
lsat-0.0.1.dist-info/RECORD
