Metadata-Version: 2.1
Name: lsat
Version: 0.0.1
Summary: A small example package
Author-email: Pedro Dal Bianco <dalbianco.pedro@gmail.com>
Project-URL: Homepage, https://github.com/midusi/LSA-T
Classifier: Programming Language :: Python :: 3
Classifier: License :: OSI Approved :: MIT License
Classifier: Operating System :: OS Independent
Requires-Python: >=3.9
License-File: LICENCE
Requires-Dist: torch
Requires-Dist: torchtext
